arduino_cli_mcp/__init__.py
arduino_cli_mcp/main.py
arduino_cli_mcp-0.1.3.dist-info/LICENSE
arduino_cli_mcp-0.1.3.dist-info/METADATA
arduino_cli_mcp-0.1.3.dist-info/WHEEL
arduino_cli_mcp-0.1.3.dist-info/entry_points.txt
arduino_cli_mcp-0.1.3.dist-info/top_level.txt
arduino_cli_mcp-0.1.3.dist-info/RECORD
