Metadata-Version: 2.2
Name: arduino-cli-mcp
Version: 0.1.3
Summary: Arduino CLI MCP Server for VSCode and GitHub Copilot integration - a LLM Machine Communication Protocol implementation
Home-page: https://github.com/oliver0804/arduino-cli-mcp
Author: Oliver
Author-email: Oliver0804 <icetzsr@gmail.com>
License: MIT
Project-URL: Homepage, https://github.com/oliver0804/arduino-cli-mcp
Project-URL: Bug Tracker, https://github.com/oliver0804/arduino-cli-mcp/issues
Project-URL: Documentation, https://github.com/oliver0804/arduino-cli-mcp#readme
Classifier: Programming Language :: Python :: 3
Classifier: License :: OSI Approved :: MIT License
Classifier: Operating System :: OS Independent
Classifier: Development Status :: 3 - Alpha
Classifier: Topic :: Software Development :: Libraries :: Python Modules
Classifier: Intended Audience :: Developers
Requires-Python: >=3.11
License-File: LICENSE
Requires-Dist: mcp
Requires-Dist: pydantic
Dynamic: author
Dynamic: home-page
Dynamic: requires-python
